{
	"name": "CopyPipeline_8ha",
	"properties": {
		"activities": [
			{
				"name": "Copy_8ha",
				"type": "Copy",
				"dependsOn": [],
				"policy": {
					"timeout": "7.00:00:00",
					"retry": 0,
					"retryIntervalInSeconds": 30,
					"secureOutput": false,
					"secureInput": false
				},
				"userProperties": [
					{
						"name": "Destination",
						"value": "modernAwardsApi"
					}
				],
				"typeProperties": {
					"source": {
						"type": "RestSource",
						"httpRequestTimeout": "00:01:40",
						"requestInterval": "00.00:00:00.010",
						"requestMethod": "GET",
						"additionalHeaders": {
							"Ocp-Apim-Subscription-Key": "52e1516623664f9b8c416309a599ea34",
							"Cache-Control": "no-cache"
						},
						"paginationRules": {
							"AbsoluteUrl.{offset}\" ": "RANGE:0:10000:1000"
						}
					},
					"sink": {
						"type": "CosmosDbSqlApiSink",
						"writeBehavior": "insert"
					},
					"enableStaging": false
				},
				"inputs": [
					{
						"referenceName": "SourceDataset_8ha",
						"type": "DatasetReference"
					}
				],
				"outputs": [
					{
						"referenceName": "DestinationDataset_8ha",
						"type": "DatasetReference"
					}
				]
			}
		],
		"annotations": [],
		"lastPublishTime": "2022-08-25T22:37:00Z"
	},
	"type": "Microsoft.DataFactory/factories/pipelines"
}